agentlin/__init__.py
agentlin/__main__.py
agentlin/app/public/chatkit.js
agentlin/app/public/index.html
agentlin/app/route_chatkit.py
agentlin/app/route_schedule.py
agentlin/app/route_task.py
agentlin/app/server.py
agentlin/app/weather/__init__.py
agentlin/app/weather/chat.py
agentlin/app/weather/constants.py
agentlin/app/weather/facts.py
agentlin/app/weather/main.py
agentlin/app/weather/memory_store.py
agentlin/app/weather/sample_widget.py
agentlin/app/weather/trans.py
agentlin/app/weather/weather.py
agentlin/code_interpreter/__init__.py
agentlin/code_interpreter/__main__.py
agentlin/code_interpreter/chart_schema.py
agentlin/code_interpreter/client.py
agentlin/code_interpreter/data_to_document_json.py
agentlin/code_interpreter/data_to_table_json.py
agentlin/code_interpreter/data_to_visual_json.py
agentlin/code_interpreter/display_document.py
agentlin/code_interpreter/display_mime.py
agentlin/code_interpreter/display_search_result.py
agentlin/code_interpreter/display_table.py
agentlin/code_interpreter/display_tool_call.py
agentlin/code_interpreter/display_visual.py
agentlin/code_interpreter/jupyter_display.py
agentlin/code_interpreter/jupyter_parse.py
agentlin/code_interpreter/jupyter_saver.py
agentlin/code_interpreter/types.py
agentlin/core/__init__.py
agentlin/core/agent_message_queue.py
agentlin/core/agent_schema.py
agentlin/core/config.py
agentlin/core/intergrations.py
agentlin/core/multimodal.py
agentlin/core/swam.py
agentlin/core/types.py
agentlin/core/usage.py
agentlin/dataset/__init__.py
agentlin/dataset/example_dataset.py
agentlin/dataset/qa_dataset.py
agentlin/dataset/sampler.py
agentlin/environment/__init__.py
agentlin/environment/__main__.py
agentlin/environment/agent_env.py
agentlin/environment/builtin/market/market.py
agentlin/environment/builtin/market/time_coordinator.py
agentlin/environment/builtin/market/trader.py
agentlin/environment/builtin/quant/alpha_expression_miner.py
agentlin/environment/builtin/quant/alpha_expression_miner_continuous.py
agentlin-0.0.26.dist-info/METADATA
agentlin-0.0.26.dist-info/WHEEL
agentlin-0.0.26.dist-info/entry_points.txt
agentlin-0.0.26.dist-info/licenses/LICENSE
agentlin-0.0.26.dist-info/RECORD
