Metadata-Version: 2.4
Name: agentlin
Version: 0.0.26
Summary: General Agent Framework by LinXueyuan
License: MIT
License-File: LICENSE
Author: LinXueyuanStdio
Author-email: 23211526+LinXueyuanStdio@users.noreply.github.com
Classifier: License :: OSI Approved :: MIT License
Classifier: Programming Language :: Python :: 2
Classifier: Programming Language :: Python :: 2.7
Classifier: Programming Language :: Python :: 3
Classifier: Programming Language :: Python :: 3.4
Classifier: Programming Language :: Python :: 3.5
Classifier: Programming Language :: Python :: 3.6
Classifier: Programming Language :: Python :: 3.7
Classifier: Programming Language :: Python :: 3.8
Classifier: Programming Language :: Python :: 3.9
Classifier: Programming Language :: Python :: 3.10
Classifier: Programming Language :: Python :: 3.11
Classifier: Programming Language :: Python :: 3.12
Classifier: Programming Language :: Python :: 3.13
Classifier: Programming Language :: Python :: 3.14
Requires-Dist: Pillow
Requires-Dist: aio-pika
Requires-Dist: beautifulsoup4
Requires-Dist: croniter
Requires-Dist: datasets
Requires-Dist: fastapi
Requires-Dist: fastmcp
Requires-Dist: google-genai
Requires-Dist: holidays
Requires-Dist: html2text
Requires-Dist: kaleido
Requires-Dist: loguru
Requires-Dist: omegaconf
Requires-Dist: openai (==2.3.0)
Requires-Dist: openai-chatkit
Requires-Dist: plotly
Requires-Dist: psutil
Requires-Dist: pylatexenc
Requires-Dist: python-dotenv
Requires-Dist: rich
Requires-Dist: ripgrep-python
Requires-Dist: sseclient
Requires-Dist: stevedore
Requires-Dist: streamlit (>=1.46.0,<2.0.0)
Requires-Dist: streamlit-markdown
Requires-Dist: ta
Requires-Dist: typer
Requires-Dist: uvicorn
Requires-Dist: websockets
Requires-Dist: xlin
